hiko/__init__.py
hiko/dask.py
hiko/time.py
hiko/version.py
hiko-0.0.6.dist-info/LICENSE
hiko-0.0.6.dist-info/METADATA
hiko-0.0.6.dist-info/WHEEL
hiko-0.0.6.dist-info/top_level.txt
hiko-0.0.6.dist-info/RECORD
