Metadata-Version: 2.1
Name: hiko
Version: 0.0.6
Summary: Execute functions in parallel using Dask & other useful stuff
Home-page: https://github.com/sarunas-girdenas/hiko
Author: Sarunas Girdenas, Chris Gell
Author-email: sgirdenas@gmail.com
License: UNKNOWN
Platform: UNKNOWN
Requires-Dist: dask[complete]
Requires-Dist: parameterized
